Imap_CLI-0.7.data/scripts/imapcli
Imap_CLI-0.7.dist-info/METADATA
Imap_CLI-0.7.dist-info/RECORD
Imap_CLI-0.7.dist-info/WHEEL
Imap_CLI-0.7.dist-info/entry_points.txt
Imap_CLI-0.7.dist-info/top_level.txt
imap_cli/__init__.py
imap_cli/config.py
imap_cli/const.py
imap_cli/copy.py
imap_cli/delete.py
imap_cli/fetch.py
imap_cli/flag.py
imap_cli/list_mail.py
imap_cli/search.py
imap_cli/string.py
imap_cli/summary.py
imap_cli/scripts/__init__.py
imap_cli/scripts/imap_api.py
imap_cli/scripts/imap_notify.py
imap_cli/scripts/imap_shell.py
imap_cli/tests/__init__.py
imap_cli/tests/test_config.py
imap_cli/tests/test_encoding.py
imap_cli/tests/test_fetch.py
imap_cli/tests/test_flag.py
imap_cli/tests/test_imapcli.py
imap_cli/tests/test_list_mail.py
imap_cli/tests/test_search.py
imap_cli/tests/test_status.py
imap_cli/tests/test_summary.py
