Metadata-Version: 2.1
Name: Imap-CLI
Version: 0.7
Summary: Set of high level mail management functions. All managed in CLI
Home-page: http://gentux.github.io/imap-cli/
Author: Romain Soufflet
Author-email: romain@soufflet.io
License: MIT License
Keywords: imap cli high level
Platform: OS Independent
Classifier: Development Status :: 3 - Alpha
Classifier: Environment :: Console
Classifier: Intended Audience :: Developers
Classifier: License :: OSI Approved :: MIT License
Classifier: Operating System :: OS Independent
Classifier: Topic :: Utilities
Classifier: Programming Language :: Python :: 2.7
Classifier: Programming Language :: Python :: 3.4
Requires-Dist: docopts (>=0.6)
Requires-Dist: mock (>=1.0.1)
Requires-Dist: future
